{
  "id": "dsbom-runtime-vfs-tracing",
  "title": "dSBOM: Non-Invasive Runtime Software Bills of Materials via Kernel VFS Tracing",
  "category": "Systems Security, C++20, Linux Kernel, VFS, CycloneDX",
  "readTime": "7",
  "date": "Jul 6, 2026",
  "excerpt": "How the dSBOM-engine intercepts process hierarchies using ptrace(2) and the Linux kernel virtual filesystem (VFS) to generate zero-overhead, injection-free software bills of materials.",
  "content": "## Eliminating Userspace Injection\n\nTraditional Software Bill of Materials (SBOM) generation relies heavily on static dependency analysis or active user-space injection/instrumentation. These methods suffer from two main flaws: they cannot capture dynamically loaded libraries executed deep within runtime branches, and they introduce undesirable latency or instability into the host application.\n\n**dSBOM-engine** sidesteps this entirely by moving the observation boundary down to the Linux kernel virtual filesystem (VFS) and tracer subsystems. It derives exact component identity, linkage, and cryptographic integrity natively from the host context, without injecting a single line of code into the target application.\n\n---\n\n## Architectural Framework\n\nThe engine relies on three core pillars to achieve atomic execution tracking without breaking isolation boundaries.\n\n### 1. Kernel Boundary Interception\nThe engine hooks target process hierarchies entirely from the host context using `ptrace(2)`. Address space transparency is maintained through an external, register-level observation loop driven by `PTRACE_SYSCALL` with `PTRACE_O_TRACESYSGOOD` enabled. \n\nThe tracing state machine decodes the x86-64 register file at every syscall entry-exit boundary by evaluating `orig_rax`:\n\n* **`SYS_execve` (59) / `SYS_execveat` (322):** Resets the per-task dynamic mapping ledger and initiates a brand new component lifecycle evaluation.\n* **`SYS_mmap` (9):** Extracts memory range length, page protection flags (`prot`), and file descriptors to track valid, file-backed virtual memory allocations.\n* **`SYS_mprotect` (10):** Monitors memory region permission transitions, detecting runtime attempts to break Write-or-Execute ($W\\wedgeX$) protections.\n\n### 2. Isolated Namespace Translation\nTo inspect targets running inside containerized runtimes (such as Docker, Podman, or containerd) without cross-boundary data leakage, file I/O operations are routed through the target process's virtual path root:\n\n```text\n/proc/[pid]/root/[canonical-internal-path]\n```\n\nThe kernel translates this path by traversing the target's mount namespace dentry cache. This structural routing allows the host-resident engine to read targets and shared libraries directly, executing static ELF analysis and verification signatures without performing `setns(2)` or `pivot_root`, keeping host filesystem isolation primitives perfectly intact.\n\n### 3. Cryptographic Integrity Pipeline\n\nThe hashing subsystem implements an allocation-free pipeline centered around a pre-allocated, thread-local OpenSSL `EVP_MD_CTX` context configured for SHA-256:\n\n    Zero Heap Allocation: The execution context is stack-allocated once per worker thread. Intermediate digests are collected directly into a fixed-size buffer and hex-encoded using a `constexpr` lookup table.\n\n    Page-Aligned Streaming: Files are read sequentially in 64 KiB page-aligned chunks using `mmap(2)` with `MAP_PRIVATE` and `MADV_SEQUENTIAL` hints, minimizing TLB pressure and eliminating runtime user-space buffer reallocations.\n\n### Output Engineering\n\nThe output generated matches strict ** CycloneDX 1.5 ** JSON records, embedding tracking metadata directly alongside concluded values derived from the kernel state loop:\n```JSON\n\n{\n  \"bomFormat\": \"CycloneDX\",\n  \"specVersion\": \"1.5\",\n  \"components\": [\n    {\n      \"type\": \"library\",\n      \"name\": \"libc.so.6\",\n      \"version\": \"dynamic-runtime\",\n      \"hashes\": [\n        { \"alg\": \"SHA-256\", \"content\": \"9bf40a540836d90c7d46c95eeb222a217597834eea29ab9e537428317c021c3a\" }\n      ],\n      \"evidence\": {\n        \"identity\": [\n          {\n            \"field\": \"path\",\n            \"concludedValue\": \"/usr/lib/libc.so.6\",\n            \"methods\": [\n              { \"technique\": \"ptrace\", \"confidence\": 1.0, \"value\": \"/usr/lib/libc.so.6\" }\n            ]\n          }\n        ]\n      }\n    }\n  ]\n}\n```"
}